{
  "accountAssociation": {
    "header": "eyJmaWQiOjE5MzkxLCJ0eXBlIjoiYXV0aCIsImtleSI6IjB4NzViQUE3OWJCYTI4OWMwMGQ5QWIwODNGMTJmNmNEMTY3NTg4NWViMyJ9",
    "payload": "eyJkb21haW4iOiJtb25hZHgyMDQ4LnZlcmNlbC5hcHAifQ",
    "signature": "oKEtlSBbb8E1S9ssTrim8GvGTxmYKAB+Rw2n1BpBkmFirNay/3LcEdF2aN0cviOmXg7GiFsOXFHyBAkMLT+Xrxw="
  },
  "frame": {
    "name": "Monad X 2048",
    "version": "1",
    "iconUrl": "https://monadx2048.vercel.app/assets/favicon.jpg",
    "homeUrl": "https://monadx2048.vercel.app/",
    "imageUrl": "https://monadx2048.vercel.app/assets/favicon.jpg",
    "splashImageUrl": "https://monadx2048.vercel.app/assets/favicon.jpg",
    "splashBackgroundColor": "#9280FA",
    "subtitle": "Purple 2048 game on Monad  ",
    "description": "Purple 2048 game X Monad by ImanPJN",
    "primaryCategory": "games",
    "screenshotUrls": [
      "https://monadx2048.vercel.app/assets/screenshot1.jpg",
      "https://monadx2048.vercel.app/assets/screenshot2.jpg"
    ],
    "tags": [
      "2048",
      "game",
      "Monad",
      "Testnet",
      "purple"
    ],
    "tagline": "Fun and addictive 2048 game!",
    "ogTitle": "Monad X 2048",
    "heroImageUrl": "https://monadx2048.vercel.app/assets/favicon.jpg",
    "ogImageUrl": "https://monadx2048.vercel.app/assets/favicon.jpg",
    "ogDescription": "Play Purple 2048 game X Monad, Fun and addictive game!",
    "castShareUrl": "https://monadx2048.vercel.app/api/share",
    "addToHomeScreenAction": {
      "type": "post_redirect",
      "name": "افزودن به Mini Apps",
      "description": "برای دسترسی سریع‌تر به این بازی",
      "postUrl": "https://monadx2048.vercel.app/"
    },
    "webhookUrl": "https://purple2048.vercel.app/api/farcaster-webhook"
  }
}
